hmpol/__init__.py
hmpol/PYSCF/__init__.py
hmpol/PYSCF/moment_tensor.py
hmpol/PYSCF/polarizability_tensor.py
hmpol/PYSCF/qdist.py
tests/PySCFmerger.py
tests/__init__.py
tests/file.py
tests/test_poltensor.py
hmpol-0.1.5.dist-info/LICENSE
hmpol-0.1.5.dist-info/METADATA
hmpol-0.1.5.dist-info/WHEEL
hmpol-0.1.5.dist-info/top_level.txt
hmpol-0.1.5.dist-info/RECORD
