Metadata-Version: 2.1
Name: hmpol
Version: 0.1.5
Summary: A package to calculate the moments and polarizabilities of molecules
Home-page: https://gitlab.com/AnoopANair/the-hmpol-project.git
Author: Anoop Ajaya Kumar Nair
Author-email: mailanoopanair@gmail.com
Classifier: License :: OSI Approved :: MIT License
Classifier: Programming Language :: Python :: 3.12
Classifier: Operating System :: OS Independent
License-File: LICENSE
Requires-Dist: pyscf
Requires-Dist: ase
